{
  "chunk_id": "cea_standard_technical_specification_500mw_chunk_0643",
  "source_doc": "CEA Standard Technical Specification 500MW",
  "source_url": "https://cea.nic.in/wp-content/uploads/2020/04/standard_tech_spec.pdf",
  "doc_type": "regulatory",
  "equipment_tags": [
    "Generator"
  ],
  "section": "",
  "page_number": 668,
  "text": "have each window as mosaic compatible. The lamp box shall have removable impact polystyrene window shall be 50 mm x 50 mm or 48mm x 48mm with 5 mm size incscription in black lettering on white background. Each annunication window shall be backlighted with two long life LED lamps The changing of lamps shall be conveniently done from the front by single removal of window. Redundant audible devices for alar ms shall be cone type or metallic horn type and shall be driven by electr onic tone generator of adjustable width and sound level. The trip alarm audible & ring back audible shall be differentiated from other alarms. ii) The annunciator sequence shall conf orm to ISA sequence ISA-2A. The number of annunciation facia windows and the provision for original input will be on as required basis. However, the minimum number of facia windows, signal input to the annunciation system shall be 25 nos. 6.12.11 Software Documentation and Software Listings i) All technical manuals, reference manuals, user\u2019s guide etc., in English required for modification/editing/addition/ deletion of features in the software of the PLC System shall be furnished. The Contractor shall furnish a comprehensive list of all system/application software documentation after system finalisation for Purchaser\u2019s review and approval. Standard Technical Specification fo r Sub- critical Thermal Powe r Project - 2x(500MW or above) Main Plant Package Section 6 (Control and Instrumentation Works) 6 - 141 ii) All The software listings including Sour ce code for application software, All special-to-project data files etc. shall be submitted by the Contractor: iii) Software Licences The Contractor shall provide software license for all software being used in DDCMIS. The software licenses shall be provided for the project (e.g. organisation or site license) and shall not be hardware/machine-specific. That is, if any hardware/machine is upgraded or changed, the same license shall hold good and it shall not be necessar y for Purchaser to seek a new license/renew license due to upgradati on/change of hardware/machine in DDCMIS at site. All licenses shall be valid for the continuous service life of the plant. iv) Software Upgrades As a customer support, the Contractor shall periodically inform the designated officer of the Purchaser about the software upgrades/new releases that would be taking place after the system is commissioned so that if required, same can be procur ed & implemented at site. Standard Technical Specification fo r Sub- critical Thermal Powe",
  "chunk_index": 643,
  "ingested_at": "2026-06-24T15:45:33.901314Z"
}