{
  "chunk_id": "cea_standard_technical_specification_500mw_chunk_0782",
  "source_doc": "CEA Standard Technical Specification 500MW",
  "source_url": "https://cea.nic.in",
  "doc_type": "technical_spec",
  "client": "",
  "equipment_tags": [
    "Turbine"
  ],
  "section": "",
  "page_number": 813,
  "text": "tubes etc. to establish their mechanical properties, and chemical compositions. ii) Nozzle forgings shall be subject to su itable heat treatment and 100% ultrasonic testing. iii) Tubes a) Tubes shall be subject to dimensional check. b) 100% eddy current test shall be carried out for tube thickness < 3.6 mm and 100% UT for tube thickness \u2265 3.6 mm. c) Tubes shall be subject to 100% hydraulic test. d) Flattening and flaring tests shall also be carried out for the tubes as per applicable codes. e) Before tubes expansion in the tube sh eets, the mockup test for expansions shall be carried out. Torque setting of expander shall be based on mock up tests. Joints shall be checked for tube thinning. iv) Tube sheets a) Tube sheets shall be subject to visual examination and dimensional check. Standard Technical Specification for Sub- critical Thermal Power Project - 2x(500MW or above) Main Plant Package Section- 8 (Quality Assurance Plan) 8 - 27 b) Impact test shall be carried out for the plate materials. c) 100% UT and 100% DP test shall be carried out after overlay and machining. In case overlay is not applicable, only 100% UT shall be carried out. d) For cladded plates, bonding shall be ch ecked by UT. Drilled tube plates shall be checked for ovality of holes, ligaments, surface finish etc. e) Tube to tube sheet weld joints sha ll be subject to 100% DP test. These joints shall also be subject to air test. v) Shell, dished ends and hemi heads a) Impact test shall be carried out for the plate materials. b) 100% UT shall be carried out on the finished and formed dished ends and hemi heads. c) Dished ends shall be subject to dimensional check after dishing. d) Knuckle portion shall be checked by 100% MPE or DPT for surface defects and check for thinning shall be carried out by UT. vi) Welding a) Root run of butt welds shall be examined by 100% DPT or MPE. b) Butt welded and full penetration joints and nozzle welds shall be checked by 100% RT or UT and 100% MPE or DPT. c) Fillet welds shall be checked by 100% MPE or DPT. d) All weldments shall be given suitable heat treatment. vii) Visual check and dimensional measurement shall be carried out on the completed equipment. viii) Completed assembly shall be pressure test ed with",
  "chunk_index": 782,
  "ingested_at": "2026-06-26T10:05:46.248902Z"
}