{
  "chunk_id": "cea_standard_technical_specification_500mw_chunk_0179",
  "source_doc": "CEA Standard Technical Specification 500MW",
  "source_url": "https://cea.nic.in/wp-content/uploads/2020/04/standard_tech_spec.pdf",
  "doc_type": "regulatory",
  "equipment_tags": [
    "Boiler",
    "Turbine",
    "Generator"
  ],
  "section": "",
  "page_number": 182,
  "text": "at rated main steam and reheat steam parameters. iii) The steam turbine generator unit shall be suitable for direct connection to steam generator having no interconnection with other units either on the boiler feed water side or main steam side. iv) The steam turbine shall have uncontro lled extractions for regenerative feed heating based on optimised cycle of the bidder. 3.1.1.3 Operational capabilities i) H.P. heaters out of service : Turbine shall be capable of continuous operation under all HP heaters out of service with maximum output commensurate with boiler heat duty corresponding to 100% BMCR operation with HP heaters in service and the same shall be demonstrated. ii) HP heaters (one string) : out of service Turbine shal l be capable of enhanced output under HP heaters (one string) out of service with boiler heat duty corresponding to 100% BMCR operation with HP heaters in service. 3 70mmHg (abs) for sea water based once through CW system Standard Technical Specification for Sub- critical Thermal Power Project - 2x(500MW or above) Main Plant Package Section- 3 (Steam Turbine and Auxiliaries) 3 - 3 iii) Over pressure operation : a) Bidder shall indicate the turbine over pressurisation (under VWO) possible and ensure corresponding continuous output of TG set. b) Turbine shall be capable of accepting variation in steam temp. and pressure as per IEC 45 in case continuous over pressure operation is possible . iv) Two shift and cyclic load : Turbine shall be suitable for two shift operation and cyclic load variation. v) Part load and start up operation : a) Turbine shall be capable of operating on constant pressure mode as well as on variable pressure mode during part load and start up operation. b) TG set shall be capable of being started from cold condition to full load operating conditions in as short time as possible. vi) House load operation : TG set shall be capable of operating on house load during sudden total export load throw off using HP and LP bypass system. Unit shall not trip on over-speed in the event of total export load throw-off. vii) No. of start ups : Expected numbers of turbine generator start- ups are given below. The design of turbine generator and the associated systems shall take care of these start ups without affecting the life of equipment adversely. No component shall be stressed beyond acceptable safe stress and fatigue",
  "chunk_index": 179,
  "ingested_at": "2026-06-24T15:45:33.901314Z"
}