{
  "chunk_id": "cea_standard_technical_specification_500mw_chunk_0642",
  "source_doc": "CEA Standard Technical Specification 500MW",
  "source_url": "https://cea.nic.in",
  "doc_type": "technical_spec",
  "client": "",
  "equipment_tags": [
    "Boiler",
    "Turbine",
    "BFP"
  ],
  "section": "",
  "page_number": 670,
  "text": "or his au thorized representative) even if the same had been conducted earlier, as clearly indicated subsequently against such tests. (b) For the rest, submission of type test results and certificate shall be acceptable provided. i. The same has been carried out by the bidder/ sub-vendor on exactly the same model /rating of equipment. ii There has been no change in the components from the offered equipment & tested equipment. iii. The test has been carried out as per the latest standards alongwith amendments as on the date of bid opening. (c) In case the approved equipment is different from the one on which the type test had been conducted ear lier or any of the above grounds, then the tests have to be repeated and the cost of such tests shall be borne by the bidder within the quoted price and no extra cost will be payable by the purchaser on this account. iii) As mentioned against certain ite ms, the test certificates for some of the items shall be reviewed and approved by the bidder or his authorized representative and the balance have to be approved by the purchaser. iv) The schedule of conduction of t ype tests/ submission of reports shall be submitted and finalized during pre-award discussion. v) For the type tests to be conducted, contractor shall submit detailed test procedure for approval by purchaser. This shall clearly specify test setup, instruments to be used, procedure, acceptance norms (wherever applicable), recording of different parameters, interval of recording precautions to be taken etc. for the tests to be carried out. vi) The bidder, shall indicate in his bid, the cost of the type test for each items only for which type tests are to be conducted specifically for this project. Standard Technical Specification for Sub- critical Thermal Power Project - 2x(500MW or above) Main Plant Package Section 6 (Control and Instrumentation Works) 6 - 143 6.13.2 Special Requirement for Solid State Equipments/ Systems The minimum type tests reports, over and above the requirements of above clause which are to be submitted for each of the major C&I systems like SG- C&I system, TG- C&I system, BOP- C&I system, Flame monitoring system, Coal feeders control and instrument ation system, Boiler flame analysis system, Electronic remote drum level monitoring system, Turbine supervisory system, BFP Turbine s upervisory instruments, Analyzer instruments, Vibration monitoring systems, etc. shall be as indicated below:",
  "chunk_index": 642,
  "ingested_at": "2026-06-26T10:05:46.248902Z"
}