{
  "chunk_id": "cea_standard_technical_specification_500mw_chunk_0396",
  "source_doc": "CEA Standard Technical Specification 500MW",
  "source_url": "https://cea.nic.in",
  "doc_type": "technical_spec",
  "client": "",
  "equipment_tags": [],
  "section": "",
  "page_number": 415,
  "text": "The tap change switch shall be thr ee phase, hand operated for simultaneous switching of similar taps on the three phases by operating on external hand wheel. ii) Arrangement shall be made for securing a nd pad-locking the tap changer in any of the working positions, and it shall not be possible for setting or padlocking it in any intermediate position. An indicati ng device shall be prov ided to show the tap in use. Standard Technical Specification for Sub- critical Thermal Power Project - 2x(500MW or above) Main Plant Package Section-5 (Electrical Works) 5 - 58 5.6.12 Fittings The following fittings (wherever applicable) sh all be provided with all the transformers, unless mentioned specifically otherwise. a) Conservator with oil filling hole and cap, isolating valve, drain valve, vent valve and oil preservation equipment as specified. b) Magnetic oil level gauge with low level alarm contacts. It shall be welded to the tank. c) Prismatic glass oil level gauge. d) Pressure relief device and Explosion Vent. e) Air release plug. f) Inspection opening and covers g) Bushing with metal parts and gaskets to suit the termination arrangement specified in Technical Parameters. h) Oil temperature indicator with alarm and trip contacts. i) Winding temperature indicator (s) with alarm and trip contacts. j) Covers, lifting eyes, transformer lifting lugs, jacking pads, towing holes, core and winding lifting lugs, supporting structure, foundation bolts etc. k) Protected type Mercury or alcohol in glass thermometer. l) Bottom and top filter valves with thread ed male adopters, bottom sampling valve and drain valve. m) Rating and diaphragm plates. n) Off circuit tap changing equipment. o) Marshalling Box p) Cable Boxes q) Buchholz Relay r) Dehydrating filter breather s) Bushing current transformers (wherever applicable) t) Earthing terminals. u) Remote WTI. It shall nor be repeater dial of local WTI v) Radiator w) Wheels x) Oil y) V/v schedule plate z) Rain hoods for B/z relay, MOG and PRV Standard Technical Specification for Sub- critical Thermal Power Project - 2x(500MW or above) Main Plant Package Section-5 (Electrical Works) 5 - 59 5.7 MOTORS All the 11kV, 3.3kV and 415V motors required for unit auxiliaries shall be provided. 5.7.1 Codes and Standards All the motors shall conform to the following standards : IS:325, IEC:60034 Three phase induction motors IS:996, IEC:60034 Single phase AC motors IS:3177, IEC600:34 Crane duty motors IS:4722 DC motors 5.7.2 General Requirements i) All the motors",
  "chunk_index": 396,
  "ingested_at": "2026-06-26T10:05:46.248902Z"
}