{
  "chunk_id": "cea_standard_technical_specification_500mw_chunk_0023",
  "source_doc": "CEA Standard Technical Specification 500MW",
  "source_url": "https://cea.nic.in/wp-content/uploads/2020/04/standard_tech_spec.pdf",
  "doc_type": "regulatory",
  "equipment_tags": [],
  "section": "",
  "page_number": 31,
  "text": "to enable unloading of bunkers on trucks at ground level. vi) Suitable couplings (Dresser or equivalent) with 410 stainless steel liner ring one on each chute between RC fe eder and mill and one on each chute between coal bunker and RC feeder. vii) Devices to detect choking/flow/no flow of coal in the coal chute between coal bunker and RC feeder. viii) Remote (UCB) pneumatic/ motor operate d shut off gate between RC feeder and coal mill. ix) A local access platform for maintenance/operation of bunker shut-off valves. Standard Technical Specification for Sub- critical Thermal Power Project - 2x(500MW or above) Main Plant Package Section- 1 (General) 1 - 6 B) Raw Coal Feeders Gravimetric type raw coal feeders with microprocessor based precision weighing and calibration devices, one for each mill. The feeders shall be complete with motor, coupling, coupling guards, base plate, foundation bolts, sliding joints, paddle type switches to detect presence or absence of coal on feeder or choking of feeder, speed variator, speed sensors, coal motion monitors, and strain gauge type weight measuring system with all instrumentation. C) Coal Pulverisers i) The coal pulverisers shall be vertical spindle type medium speed mills (like pressurized type bowl mills, ball and race mills such as MBF/MPS/MRS mills etc. or the approved equivalent). The coal pulverisers shall conform to sizing/ standby requirements stipulated elsewhere in the specification. ii) The coal pulverisers shall be installed on rigid RCC foundations. iii) Each pulveriser shall be complete with all wear parts, grinding elements, classifier and shall be provided with platforms around the pulveriser, lubrication systems (comprised of 2x100% pumps, 2x100% cooler and 2x100% filters for each pulveriser), drive motors, auxiliary gear, instrument tapping points and any other equipment necessary for safe and efficient operation of pulveriser. Adequate number of temperature sensors, local indicators and signaling contacts for bearings and lube oil systems shall be provided. Independent purge meters, air filter cum regulator sets, and required local gauges and switches for milling system shall be provided at air inlet of each coal pulveriser. Adequate number of thermocouple type detection system as a composite and complete unit with all required accessories with adequa te redundancy shall be provided. iv) Proven fire detection and fire extinguishing systems in line with the standard practice of the manufacturer shall be provided. In case of CO 2/N2 based system, the scope of supply shall also include the required cylinder/piping",
  "chunk_index": 23,
  "ingested_at": "2026-06-24T15:45:33.901314Z"
}