{
  "chunk_id": "cea_standard_technical_specification_500mw_chunk_0149",
  "source_doc": "CEA Standard Technical Specification 500MW",
  "source_url": "https://cea.nic.in",
  "doc_type": "technical_spec",
  "client": "",
  "equipment_tags": [
    "Boiler",
    "Generator"
  ],
  "section": "",
  "page_number": 157,
  "text": "low fuel oil pressure. For drain oil pumps, auto start and shutdown facility shall be provided in conjunc tion with level in the drain oil tanks. b) Interlock shall be provided for au tomatic purge before light up and after failure to first oil burner operation. c) Separate flame viewing opening/ facility shall be provided for boiler operation and for flame monitoring at each burner from out side. The provision shall be made to keep the system cool below 75 0C and to keep the optical system clean during firing/non firing by pressurised air. d) Adequate instrumentation such as temperature, pressure, differential pressure, flow transmitters, switches for independent high and low signalling contacts required for burner management system and other interlock/alarm shall be provided for interfacing with other systems/ equipments. e) Adequate potential free contacts shall be provided for status of individual pumps. 2.2.9.2 Fuel oil drain and condensate system i) Design and construction of drain o il tank(s) and condensate tank shall comply with following requirements: Drain oil tank Condensate flash tank a) Medium to be Heavy fuel oil Condensate water/ stored (HPSLSHS/HFO) flash steam and LDO Standard Technical Specification for Sub- critical Thermal Power Project - 2x(500MW or above) Main Plant Package Section- 2 (Steam Generator and Auxiliaries) 2 - 56 b) No. of tanks Two (2) in boiler One (1) area and one (1) in FO pressurizing pump house area. c) Tank capacity 6m3 (each) in SG 6m 3 area and 10m3 in FO pressurizing pump house area. d) Design and IS:800 IS: 2825 Class-II construction code or equivalent e) Design temperature 120 0C (minimum) 215 0C (minimum) f) Tank design pressure - As per applicable code g) Type of Rectangular Vertical cylindrical construction with dished ends h) Material of As per IS:2062 As per IS:2825/ construction ASME Sec. VIII i) Corrosion allowance 1.8 mm 1.8 mm j) Insulation Required Required k) Nominal - Vent pipe of 250 Nb venting capacity (min.) and 3.5 m height l) Heater tube 50 Nb tubes as - material per IS1239 (heavy grade) or ASTM 106 Gr. B ii) The design, fabrication, erection, commissioning and testing of the tanks shall be conform to IS:2825. iii) Steam coil heaters shall be provided at the bottom of drain oil tanks to maintain the oil temperature to facilita tes its pumping. The heaters shall be sized considering ambient air temperature of 10 0C. Total",
  "chunk_index": 149,
  "ingested_at": "2026-06-26T10:05:46.248902Z"
}