{
  "chunk_id": "cea_standard_technical_specification_500mw_chunk_0393",
  "source_doc": "CEA Standard Technical Specification 500MW",
  "source_url": "https://cea.nic.in/wp-content/uploads/2020/04/standard_tech_spec.pdf",
  "doc_type": "regulatory",
  "equipment_tags": [],
  "section": "",
  "page_number": 411,
  "text": "shall be 1676 mm in both directions. Flanged wheels shall be spaced accordingly. Wheels shall be provided with suitable b earings, which will resist rust and corrosion and shall be equipped with fittings for lubrication. It shall be possible to swivel the wheels in two directions, at right angels to or parallel to the main axis of the transformers. b) Jacking pads shall be provided on the transformer. It shall be possible to change the direction of the wh eels through 90 degree when the transformer is lifted on jacks to permit movement of the transformer both in longitudinal and transverse directions. c) Suitable hydraulic (synchronous) jacks (4 nos.) for lifting the transformer shall be supplied. iii) Conservator tank a) The conservator tank shall have adequate capacity to accommodate oil preservation system and volumetric expansion of the total cold oil volume in the transformer and cooling equipment for a change in temperature from minimum ambient temperature as per IS. b) The conservator shall be fitted with magnetic oil level gauge with two independent low level electrically insulated alarm contacts. c) Each conservator vessel/ air bag shall be fitted with a silica gel filter breather. iv) Pressure relief device and explosion vent a) For all transformers, the conventional diaphragm type of explosion vent shall be provided. Standard Technical Specification for Sub- critical Thermal Power Project - 2x(500MW or above) Main Plant Package Section-5 (Electrical Works) 5 - 54 b) In addition to the explosion vent, pressure relie f device shall be provided for transformers rated 2 MVA and above which shall be of sufficient size for rapid release of any pressure that may be generated within the tank and which may result in damage of the equipment. c) An extension pipe shall be fitted above the device such as to direct the major flow of ejected oil down wards a nd shall be fitted so as to permit its removal without disturbing the device or its flange fixings. v) Buchholz relay A double float type Buchholz relay confor ming to IS:3637 shall be provided. All gas evolved in the transformer shall coll ect in this relay. The relay shall be provided with a test cock suitable for a flexible pipe connection for checking its operation. A copper tube shall be connected from the gas collector to a valve located about 1200 mm above ground leve l to facilitate sampling with the",
  "chunk_index": 393,
  "ingested_at": "2026-06-24T15:45:33.901314Z"
}