{
  "chunk_id": "cea_standard_technical_specification_500mw_chunk_0450",
  "source_doc": "CEA Standard Technical Specification 500MW",
  "source_url": "https://cea.nic.in",
  "doc_type": "technical_spec",
  "client": "",
  "equipment_tags": [],
  "section": "",
  "page_number": 469,
  "text": "50x6mm GS flat h) Crane, rails, rail tracks and other non-current carrying metal parts 25x6mm GS flat v) Metallic frame of all electrical equipm ent shall be earthed by two separate and distinct connections to earthing system , each of 100% capacity, Crane rails, tracks, metal pipes and conduits shall also be effectively earthed at two points. Steel RCC columns, metallic stairs, a nd rails etc. of the building housing electrical equipment shall be connected to the nearby earthing grid conductor by one earthing ensured by bonding the differe nt sections of hand rails and metallic stairs. Metallic sheaths/screens, and armour of multi-core cables shall be earthed at both ends. Metallic Sheaths and armour of single core cables shall be earthed at switchgear end only. Every alternate post of the switchyard fence shall be connected to earthing grid by one GS flat and gates by flexible lead to the earthed post. Railway tracks within the plant ar ea shall be bonded across fish plates and connected to earthing grid at several locations. Portable tools, appliances and welding equipment shall be earthed by flexible insulated cable. vi) Each continuous laid lengths of cable tray shall be earthed at minimum two places by GS flats to earthing system, the distance between earthing points shall not exceed 30 metre. Wherever earth mat is not available Contractor shall do the necessary connections by driving an earth electrode in the ground. Standard Technical Specification for Sub- critical Thermal Power Project - 2x(500MW or above) Main Plant Package Section-5 (Electrical Works) 5 - 112 vii) Neutral connections and metallic c onduits/ pipes shall not be used for the equipment earthing. Lightning protection system down conductors shall not be connected to other earthing conductors above the ground level. viii) Connections between earth leads and e quipment shall normally be of bolted type. Contact surfaces shall be thoroughly cl eaned before connections. Equipment bolted connections after being tested a nd checked shall be painted with anti corrosive paint/compound. ix) Suitable earth risers shall be provided a bove finished floor/ ground level, if the equipment is not available at the time of laying of main earth conductor. x) Connections between equipment earthing leads and between main earthing conductors shall be of welded type. Fo r rust protection the welds should be treated with red lead compound and afterwards thickly coated with bitumen compound. All welded connections shall be made",
  "chunk_index": 450,
  "ingested_at": "2026-06-26T10:05:46.248902Z"
}