{
  "chunk_id": "cea_standard_technical_specification_500mw_chunk_0449",
  "source_doc": "CEA Standard Technical Specification 500MW",
  "source_url": "https://cea.nic.in/wp-content/uploads/2020/04/standard_tech_spec.pdf",
  "doc_type": "regulatory",
  "equipment_tags": [],
  "section": "",
  "page_number": 467,
  "text": "route markers and joint markers. Laying of cables and providing protective covering shall be as per IS:1255. - RCC cable route and RCC joint markers shall be provided wherever required. The voltage grade of the higher voltage cables in route shall be engraved on the marker. Location of underground cable joints shall be indicated with cable marker with an additional inscription \u201cCable Joint\u201d. The marker shall project 150 mm above ground and shall be spaced at an interval of 30 meters and at every change in direction. They shall be located on both sides of road crossings and drain crossings. Top of cable marker/joint marker shall be sloped to avoid accumulation of water/dust on marker. p) Cable tags shall be provided on all cables at each end (just before entering the equipment enclosure), on both sides of a wall or floor crossing, on each duct/conduit entry, and at every 20 meters in cable tray/trench runs. Cable tags shall also be provided inside the switchgear, motor control centers, control and relay panels etc. where a number of cables enter together through a gland plate. Cable tag shall be of rectangular shape for power cables and control cables. Cable tag shall be of 2 mm thick aluminum with number punched on it and securely attached to the cable by not less than two turns of 20 SWG GI wire conforming to IS:280. Alternatively, cable tags made of nylon, cable marking ties of \u2018TY-CAB\u2019 or equivale nt type with cable number heat stamped on the cable tags may also be provided. q) While crossing the floors, un-arm oured cables shall be protected in conduits upto a height of 500 mm from floor level if not laid in tray. Standard Technical Specification for Sub- critical Thermal Power Project - 2x(500MW or above) Main Plant Package Section-5 (Electrical Works) 5 - 110 v) Cable terminations and connections a) The termination and connection of cables shall be done strictly in accordance with cable termination kit manufacturer instructions, drawings etc. Cable jointer shall be qualified to carryout satisfactory cable jointing/ termination. b) Work shall include all clamps, fittings etc. and clamping, fitting, fixing, plumbing, soldering, drilling, cutting, taping, preparation of cable end, crimping of lug, insulated sleeving over control cable lugs, heat shrinking (where applicable), connec ting to cable terminal, shorting and grounding as required to complete the job. c) The equipment will be generally pr ovided",
  "chunk_index": 449,
  "ingested_at": "2026-06-24T15:45:33.901314Z"
}