{
  "chunk_id": "cea_standard_technical_specification_500mw_chunk_0445",
  "source_doc": "CEA Standard Technical Specification 500MW",
  "source_url": "https://cea.nic.in/wp-content/uploads/2020/04/standard_tech_spec.pdf",
  "doc_type": "regulatory",
  "equipment_tags": [],
  "section": "",
  "page_number": 464,
  "text": "Project - 2x(500MW or above) Main Plant Package Section-5 (Electrical Works) 5 - 106 e) In certain cases it may be necessary to site fabricate portions of trays, supports and other non standard bends where the normal prefabricated trays, supports and accessories may not be suitable. In such cases the Contractor shall fabricate at site suitable sections of trays, supports and accessories to make the installation complete for the specific purpose after obtaining Project Manager's prior approval, which shall be neat in appearance and shall match with the prefabricated sections in the dimensions. They shall be applied with one coat of red lead primer, one coat of oil primer followed by two finishing coats of aluminium paint. ii) Conduits/ Pipes/ Ducts installation a) All openings in the floor/ roof/ wall/ cable tunnel/ cable trenches made for conduit installation shall be sealed and made water proof. b) GI pull wire of adequate size sh all be laid in all conduits before installation. Metallic conduit runs at termination shall have two lock nuts wherever required for junction boxes etc. c) Conduit runs/sleeves shall be provi ded with PVC bushings having round edge at each end. All conduits/ pipes shall have their ends closed by caps until cables are pulled. After cables are pulled, the ends of conduits/ pipes shall be sealed with Glass-w ool/ Cement Mortar/ Putty to prevent entrance of moisture and foreign material d) Exposed conduit/ pipe shall be ade quately supported by racks, clamps, straps or by other approved mean s. Conduits / pipe support shall be installed square and true to line and grade with an average spacing between the supports as given below, unless specified otherwise Conduit/ pipe size (dia) Spacing Upto 40 mm 1.0 m 50 mm 2.0 m 65-85 mm 2.5 m 100 mm 3.0 m iii) Junction boxes installation Junction boxes shall be mounted at a height of 1200mm above floor level or as specified in the drawings or as decided by Project Manager and shall be adequately supported/mounted on masonry wall by means of anchor fasteners/ expandable bolts or shall be mounted on an angle, plate or other structural supports fixed to floor, wall, ceiling or equipment foundations. Standard Technical Specification for Sub- critical Thermal Power Project - 2x(500MW or above) Main Plant Package Section-5 (Electrical Works) 5 - 107 iv) Cable installation a) Cable installation shall be carried out as per IS:1255",
  "chunk_index": 445,
  "ingested_at": "2026-06-24T15:45:33.901314Z"
}