{
  "chunk_id": "cea_standard_technical_specification_500mw_chunk_0494",
  "source_doc": "CEA Standard Technical Specification 500MW",
  "source_url": "https://cea.nic.in/wp-content/uploads/2020/04/standard_tech_spec.pdf",
  "doc_type": "regulatory",
  "equipment_tags": [
    "Turbine",
    "Generator"
  ],
  "section": "",
  "page_number": 517,
  "text": "Fuel piping c) Tachometer/RPM indicator d) Lubricating oil cooler (if applicable) e) Exhaust silencer and piping f) Fuel and lubricating oil filters, air filters. g) Temperature gauges for water and lubricating oil and pressure gauges for lubricating oil. h) Hand barring gear. i) Necessary foundation bolts and base channels for the engine, alternator, fuel service tank and for all other equipment included in this package. j) Base frames k) Platforms and hand railing and access ladder (if applicable) l) Starting equipment m) Protective equipment preferably in the form of fuel cut-off solenoid and suitable relays to protect the engi ne against low lubrication pressure. n) Lifting attachment for lifting the complete set or the engine alternator separately. o) Radiator/ Heat Exchanger. 5.16.7 Generator i) The generator shall be of totally enclo sed or screen protected drip proof and self air cooled type. The generator shall be driven by the diesel engine specified above and shall match the same in all r espects. The generator shall conform to IS-4722, IEC-60034. ii) AC generator shall be supplied along with excitation system, AVR and include all necessary auxiliaries. iii) The Generator shall be star connected , 3-phase, 50Hz synchronous generator and shall have a continuous rating. The operating conditions shall be as follows: a) Voltage 415V b) Frequency 50Hz (+3 to -5%) c) Power factor 0.80 Standard Technical Specification for Sub- critical Thermal Power Project - 2x(500MW or above) Main Plant Package Section-5 (Electrical Works) 5 - 160 iv) The generator stator and rotor windi ngs core insulation and all connections including main and neutral leads shall have class-F or better insulation. v) Resistance element temperature detector shall be installed at the following locations : a) 6 nos. duplex or 12 nos. simplex RTD\u2019s in stator windings. b) 1 no. RTD element in each bearing. vi) Suitably rated 240V, single phase, 50Hz, space heaters located in lower part of alternator shall be provided to maintain the internal temperature above the dew point to prevent moisture condensation on the insulation when the set is not running. vii) Separate terminal boxes shall be provide d for phase and neutral side of leads. The terminal boxes shall be dust proof, w eather proof phase segregated double walled (metallic as well as insulated barriers) ha ving degree of protection of IP-54 as per IS: 13947. viii) The terminal box shall be of sufficient size to conveniently terminate",
  "chunk_index": 494,
  "ingested_at": "2026-06-24T15:45:33.901314Z"
}