{
  "chunk_id": "cea_standard_technical_specification_500mw_chunk_0396",
  "source_doc": "CEA Standard Technical Specification 500MW",
  "source_url": "https://cea.nic.in/wp-content/uploads/2020/04/standard_tech_spec.pdf",
  "doc_type": "regulatory",
  "equipment_tags": [],
  "section": "",
  "page_number": 414,
  "text": "be brought out on a bushing along with the 433V phase terminal to from a 4 wire system for the 433V. Neutral CTs shall be located in the lead coming out of the winding and location of these CTs shall not be inside the tank. d) The neutral terminal of secondary shall be brought out through an outdoor bushing. Further this neutral terminal shall be connected by a copper flat of size 50 mm x 6 mm, which shall be brough t down upto 100 mm above ground. The copper flat shall be insulated and supported from the tank body. ii) Cable boxes a) Wherever cable connections are specifi ed, suitable cable boxes shall be provided and shall be air insulated. b) Cable boxes shall have drilled gland plate of adequate size to receive cables and to allow easy termination. c) Removable drilled gland planes shall be provided in the cable boxes. d) The additional supports for the cab le boxes shall be galvanised iron. e) The contractor shall provide earthing terminals on the cable box, to suit 50mmx6 mm GI flat. Standard Technical Specification for Sub- critical Thermal Power Project - 2x(500MW or above) Main Plant Package Section-5 (Electrical Works) 5 - 57 iii) Bus duct a) Wherever Bus duct termination is speci fied a flanged throat or equivalent- connection shall be provided for termina tion of bus duct enclosure. The winding termination shall be outdoor type bush ing. The material of the bus duct termination arrangement of the transf ormer shall be nonmagnetic. The bus duct may be either phase-segregated or non-segregated. b) Tolerance permissible for the height of terminals and bus duct flange location specified for bus duct termination over ground level is \u00b15mm. Contractor has to ensure that radiator, conservator and expl osion vent do not obstruct the path of the bus-ducts. 5.6.9 Current Transformers i) The protection CT\u2019s on neutral of transformers and neutral grounding transformers shall be bushing mounted. It shall be possible to remove the turret mounted CT\u2019s from the transformer tank without removing the tank cover. ii) The current transformers sh all be comply with IS:2705. iii) All secondary leads of bushing mounted CT\u2019s shall be brought to a terminal box near each bushing and then wired upto transformer marshalling box. iv) The CT terminals shall have shorting facility. 5.6.10 Marshalling box i) A sheet steel weather, vermin and dust proof marshalling",
  "chunk_index": 396,
  "ingested_at": "2026-06-24T15:45:33.901314Z"
}