{
  "chunk_id": "cea_standard_technical_specification_500mw_chunk_0713",
  "source_doc": "CEA Standard Technical Specification 500MW",
  "source_url": "https://cea.nic.in",
  "doc_type": "technical_spec",
  "client": "",
  "equipment_tags": [],
  "section": "",
  "page_number": 744,
  "text": "concrete to be deposited from a height exceeding 1.5 m. h) Concrete which has partially hardened shall not be exposed to injurious vibration or shock, except for controlled re-vibration where specified. When concreting of a certain large structural element is specified strictly as to be poured continuously, then the concreting operations shall be organized for day and night working, in long shifts, as necessary. iii) Compaction and mechanical vibration of concrete As concrete is being placed it shall be compacted by mechanical vibrators complying with IS: 2505, IS: 2506, IS: 2514 and IS: 4656, to obtain a dense material free from honeycombing, free from water and air holes. The contractor shall ensure that the vibrators are used in such a manner that the reinforcement is not disp laced, the formwork not damaged and no segregation caused, but complete compaction of the concrete is achieved. iv) Finish of concrete The concrete face shall have the finishes indicated on the drawings or in the present specification. The finished surface of th e concrete shall be sound, solid and free from honeycombing, protuberances, air holes or exposed aggregate. No plastering, cement wash, mortar or paint shall be applied to cover defective concrete surfaces. v) Construction, expansion and contraction joints a) Construction joints \u2022 The number of construction joints should be kept as low as possible consistent with reasonable precautions against shrinkage. Concreting should be carried out continuously up to construction joints. Standard Technical Specification for Sub- critical Thermal Power Project - 2x(500MW or above) Main Plant Package Section- 7 (Civil Works) 7 - 68 \u2022 Where it is necessary to introduce construction joints, careful consideration should be given to their exact location, which should be indicated on the drawings. Altern atively, the location of joints should be subject to agreement between the Purchaser and the Contractor before any work commences. Construction joints should be at right angles to the general direction of the member and should take due account of shear and other stresses. \u2022 Concrete should not be allowed to run to a feather edge and vertical joints should be formed against a stop board. \u2022 The top surface of a layer of concrete should be level and reasonably flat unless design considerations make this undesirable. Joint lines should be so arranged that they coincide with features of the finished work. \u2022 If a kicker (i.e. a starter stub) is used it",
  "chunk_index": 713,
  "ingested_at": "2026-06-26T10:05:46.248902Z"
}